<?xml version="1.0" encoding="UTF-8"?>
<objects serializationModel="Studio.02.02.00">
	<object class="AudioFile" id="{40c6acf1-da08-4963-8176-46950aef5962}">
		<property name="assetPath">
			<value>SFX/Muffin/Muffin Bark/Muffin Barking 4.wav</value>
		</property>
		<property name="frequencyInKHz">
			<value>24</value>
		</property>
		<property name="channelCount">
			<value>2</value>
		</property>
		<property name="length">
			<value>0.54525000000000001</value>
		</property>
		<relationship name="masterAssetFolder">
			<destination>{bb2d63ea-aba5-4927-b879-b351a7f2ecf3}</destination>
		</relationship>
	</object>
</objects>
